wdn_knowledge_graph/__init__.py
wdn_knowledge_graph/knowledge_graph.py
wdn_knowledge_graph/wdn_ontology.ttl
wdn_knowledge_graph-1.1.9.dist-info/licenses/LICENSE
wdn_knowledge_graph-1.1.9.dist-info/METADATA
wdn_knowledge_graph-1.1.9.dist-info/WHEEL
wdn_knowledge_graph-1.1.9.dist-info/entry_points.txt
wdn_knowledge_graph-1.1.9.dist-info/top_level.txt
wdn_knowledge_graph-1.1.9.dist-info/RECORD
