Metadata-Version: 2.4
Name: wdn-knowledge-graph
Version: 1.1.9
Summary: A package for creating knowledge graphs from water distribution network data.
Home-page: https://github.com/DiTEC-project/wdn-knowledge-graph
Author: Erkan Karabulut
Author-email: e.karabulut@uva.nl
Classifier: Programming Language :: Python :: 3
Classifier: License :: OSI Approved :: MIT License
Classifier: Operating System :: OS Independent
Requires-Python: >=3.6
License-File: LICENSE
Requires-Dist: networkx
Requires-Dist: wntr
Requires-Dist: rdflib
Dynamic: author
Dynamic: author-email
Dynamic: classifier
Dynamic: description
Dynamic: description-content-type
Dynamic: home-page
Dynamic: license-file
Dynamic: requires-dist
Dynamic: requires-python
Dynamic: summary
